{
  "@context": [
    "http://www.w3.org/ns/csvw"
  ],
  "tables": [
    {
      "url": "/data/SHAPES.csv",
      "dialect": {
        "header": false
      },
      "tableSchema": {
        "primaryKey": "shape_id,shape_pt_sequence",
        "columns": [
          {
            "datatype": "string",
            "titles": "shape_id"
          },
          {
            "datatype": "decimal",
            "titles": "shape_pt_lat"
          },
          {
            "datatype": "decimal",
            "titles": "shape_pt_lon"
          },
          {
            "datatype": "integer",
            "titles": "shape_pt_sequence"
          }
        ],
        "rowTitles": [
          "shape_id",
          "shape_pt_lat",
          "shape_pt_lon",
          "shape_pt_sequence",
          "shape_dist"
        ],
        "foreignKeys": []
      },
      "filteredRowTitles": [
        "shape_id",
        "shape_pt_lat",
        "shape_pt_lon",
        "shape_pt_sequence"
      ]
    }
  ]
}